armaio/__init__.py
armaio/_version.py
armaio/binary.py
armaio/py.typed
armaio-0.0.1.dist-info/METADATA
armaio-0.0.1.dist-info/WHEEL
armaio-0.0.1.dist-info/licenses/LICENSE
armaio-0.0.1.dist-info/RECORD
