Metadata-Version: 2.4
Name: armaio
Version: 0.0.1
Summary: IO modules for handling Arma 3 file formats.
Project-URL: Repository, https://github.com/MrClock8163/armaio
Project-URL: Issues, https://github.com/MrClock8163/armaio/issues
Author-email: MrClock <mrclock8163@gmail.com>
License-Expression: GPL-3.0
License-File: LICENSE
Keywords: arma3,bi,p3d,paa,rtm
Classifier: Development Status :: 3 - Alpha
Classifier: Intended Audience :: Developers
Classifier: License :: OSI Approved :: GNU General Public License v3 (GPLv3)
Classifier: Operating System :: OS Independent
Classifier: Programming Language :: Python
Classifier: Programming Language :: Python :: 3
Classifier: Programming Language :: Python :: 3.11
Classifier: Programming Language :: Python :: 3.12
Classifier: Programming Language :: Python :: 3.13
Classifier: Programming Language :: Python :: 3.14
Classifier: Topic :: Games/Entertainment
Classifier: Topic :: Software Development
Classifier: Topic :: Software Development :: Libraries
Classifier: Topic :: Software Development :: Libraries :: Python Modules
Classifier: Typing :: Typed
Requires-Python: >=3.11
